tnsa_api_text/__init__.py
tnsa_api_text/client.py
tnsa_api_text-1.0.1.dist-info/METADATA
tnsa_api_text-1.0.1.dist-info/WHEEL
tnsa_api_text-1.0.1.dist-info/top_level.txt
tnsa_api_text-1.0.1.dist-info/RECORD
